imreg/__init__.py
imreg/imreg.py
imreg/py.typed
imreg-2025.1.1.dist-info/LICENSE
imreg-2025.1.1.dist-info/METADATA
imreg-2025.1.1.dist-info/WHEEL
imreg-2025.1.1.dist-info/top_level.txt
imreg-2025.1.1.dist-info/RECORD
